README.md
setup.cfg
setup.py
django_inventor.egg-info/PKG-INFO
django_inventor.egg-info/SOURCES.txt
django_inventor.egg-info/dependency_links.txt
django_inventor.egg-info/requires.txt
django_inventor.egg-info/top_level.txt
inventor/__init__.py
inventor/settings.py
inventor/urls.py
inventor/utils.py
inventor/views.py
inventor/contrib/__init__.py
inventor/contrib/comments/__init__.py
inventor/contrib/comments/forms.py
inventor/contrib/comments/models.py
inventor/contrib/comments/migrations/0001_initial.py
inventor/contrib/comments/migrations/__init__.py
inventor/contrib/comments/templatetags/__init__.py
inventor/contrib/comments/templatetags/comments_contrib.py
inventor/core/__init__.py
inventor/core/accounts/__init__.py
inventor/core/accounts/admin.py
inventor/core/accounts/forms.py
inventor/core/accounts/managers.py
inventor/core/accounts/models.py
inventor/core/accounts/urls.py
inventor/core/accounts/utils.py
inventor/core/accounts/views.py
inventor/core/accounts/migrations/0001_initial.py
inventor/core/accounts/migrations/__init__.py
inventor/core/bookings/__init__.py
inventor/core/bookings/admin.py
inventor/core/bookings/mixins.py
inventor/core/bookings/models.py
inventor/core/bookings/migrations/0001_initial.py
inventor/core/bookings/migrations/__init__.py
inventor/core/lexicons/__init__.py
inventor/core/lexicons/admin.py
inventor/core/lexicons/models.py
inventor/core/lexicons/querysets.py
inventor/core/lexicons/signals.py
inventor/core/lexicons/migrations/0001_initial.py
inventor/core/lexicons/migrations/__init__.py
inventor/core/listings/__init__.py
inventor/core/listings/admin.py
inventor/core/listings/filters.py
inventor/core/listings/managers.py
inventor/core/listings/mixins.py
inventor/core/listings/urls.py
inventor/core/listings/views.py
inventor/core/listings/migrations/0001_initial.py
inventor/core/listings/migrations/0002_auto_20200309_1403.py
inventor/core/listings/migrations/0003_auto_20200309_1405.py
inventor/core/listings/migrations/__init__.py
inventor/core/listings/models/__init__.py
inventor/core/listings/models/general.py
inventor/core/listings/models/listing_types.py
inventor/management/__init__.py
