Metadata-Version: 1.2
Name: django-inventor
Version: 0.2.0
Summary: Directory listing Django app
Home-page: https://github.com/PragmaticMates/django-inventor
Author: Pragmatic Mates
Author-email: info@pragmaticmates.com
Maintainer: Pragmatic Mates
Maintainer-email: info@pragmaticmates.com
License: GNU General Public License (GPL)
Keywords: django directory listing catalog map
Platform: UNKNOWN
Classifier: Programming Language :: Python
Classifier: Programming Language :: Python :: 3.6
Classifier: Operating System :: OS Independent
Classifier: Environment :: Web Environment
Classifier: Intended Audience :: Developers
Classifier: Framework :: Django
Classifier: License :: OSI Approved :: GNU General Public License (GPL)
Classifier: Development Status :: 3 - Alpha
